ipkg/__init__.py
ipkg/cmd/main.py
ipkg/config/__init__.py
ipkg/config/path.py
ipkg/logging.py
ipkg/pkg/__init__.py
ipkg/pkg/btop/__init__.py
ipkg/pkg/btop/install.py
ipkg/pkg/btop/remove.py
ipkg/pkg/conda/__init__.py
ipkg/pkg/conda/install.py
ipkg/pkg/conda/remove.py
ipkg/shutils/__init__.py
ipkg/shutils/download.py
ipkg/shutils/extract.py
ipkg/shutils/mkdir.py
ipkg/shutils/remove.py
ipkg/shutils/run.py
ipkg/utils/__init__.py
ipkg/utils/github.py
ipkg/utils/pkg.py
ipkg/utils/typer.py
ipkg-0.2.0.dist-info/LICENSE
ipkg-0.2.0.dist-info/METADATA
ipkg-0.2.0.dist-info/WHEEL
ipkg-0.2.0.dist-info/RECORD
